sage/__init__.py
sage/api/__init__.py
sage/api/base_environment.py
sage/api/connected_streams.py
sage/api/datastream.py
sage/api/local_environment.py
sage/api/remote_environment.py
sage/api/function/__init__.py
sage/api/function/base_function.py
sage/api/function/batch_function.py
sage/api/function/comap_function.py
sage/api/function/filter_function.py
sage/api/function/flatmap_collector.py
sage/api/function/flatmap_function.py
sage/api/function/future_function.py
sage/api/function/join_function.py
sage/api/function/kafka_source.py
sage/api/function/keyby_function.py
sage/api/function/lambda_function.py
sage/api/function/map_function.py
sage/api/function/simple_batch_function.py
sage/api/function/sink_function.py
sage/api/function/source_function.py
sage/cli/__init__.py
sage/cli/cluster_manager.py
sage/cli/config_manager.py
sage/cli/deploy.py
sage/cli/deployment_manager.py
sage/cli/extensions.py
sage/cli/head_manager.py
sage/cli/job.py
sage/cli/jobmanager_controller.py
sage/cli/main.py
sage/cli/setup.py
sage/cli/worker_manager.py
sage/examples/api/basic_usage.py
sage/kernels/core/__init__.py
sage/kernels/core/pipeline.py
sage/kernels/core/py.typed
sage/kernels/core/operator/__init__.py
sage/kernels/core/operator/base_operator.py
sage/kernels/core/operator/batch_operator.py
sage/kernels/core/operator/comap_operator.py
sage/kernels/core/operator/filter_operator.py
sage/kernels/core/operator/flatmap_operator.py
sage/kernels/core/operator/future_operator.py
sage/kernels/core/operator/join_operator.py
sage/kernels/core/operator/keyby_operator.py
sage/kernels/core/operator/map_operator.py
sage/kernels/core/operator/sink_operator.py
sage/kernels/core/operator/source_operator.py
sage/kernels/core/service/base_service.py
sage/kernels/core/transformation/__init__.py
sage/kernels/core/transformation/base_transformation.py
sage/kernels/core/transformation/batch_transformation.py
sage/kernels/core/transformation/comap_transformation.py
intsage_kernel-1.0.1.dist-info/METADATA
intsage_kernel-1.0.1.dist-info/WHEEL
intsage_kernel-1.0.1.dist-info/entry_points.txt
intsage_kernel-1.0.1.dist-info/top_level.txt
intsage_kernel-1.0.1.dist-info/RECORD
