Metadata-Version: 2.4
Name: intsage-kernel
Version: 1.0.1
Summary: SAGE Framework - 统一内核 (Core + Runtime + Utils + CLI)
Author-email: IntelliStream Team <intellistream@outlook.com>
License: MIT
Project-URL: Homepage, https://github.com/intellistream/SAGE
Project-URL: Repository, https://github.com/intellistream/SAGE.git
Project-URL: Documentation, https://intellistream.github.io/SAGE-Pub/
Project-URL: Issues, https://github.com/intellistream/SAGE/issues
Keywords: data,reasoning,kernel,dataflow,llm,ml,framework,rag,intellistream,cli,ai,sage
Classifier: Development Status :: 4 - Beta
Classifier: Intended Audience :: Developers
Classifier: Intended Audience :: Science/Research
Classifier: License :: OSI Approved :: MIT License
Classifier: Operating System :: OS Independent
Classifier: Programming Language :: Python :: 3
Classifier: Programming Language :: Python :: 3.10
Classifier: Programming Language :: Python :: 3.11
Classifier: Programming Language :: Python :: 3.12
Classifier: Topic :: Scientific/Engineering :: Artificial Intelligence
Classifier: Topic :: Software Development :: Libraries :: Python Modules
Classifier: Topic :: System :: Distributed Computing
Requires-Python: >=3.10
Requires-Dist: pyyaml==6.0.2
Requires-Dist: python-dotenv==1.1.1
Requires-Dist: python_multipart==0.0.20
Requires-Dist: dill==0.4.0
Requires-Dist: ray==2.48.0
Requires-Dist: grpcio==1.74.0
Requires-Dist: protobuf==6.31.1
Requires-Dist: msgpack==1.1.1
Requires-Dist: torch==2.7.1
Requires-Dist: torchvision==0.22.1
Requires-Dist: httpx==0.28.1
Requires-Dist: socksio==1.0.0
Requires-Dist: psutil==6.1.0
Requires-Dist: numpy==2.2.6
Requires-Dist: Cython==3.1.2
Requires-Dist: pybind11==3.0.0
Requires-Dist: aioboto3==14.1.0
Requires-Dist: fastapi==0.115.12
Requires-Dist: uvicorn==0.34.3
Requires-Dist: h11==0.16.0
Requires-Dist: requests==2.32.4
Requires-Dist: aiohappyeyeballs==2.6.1
Requires-Dist: aiosignal==1.4.0
Requires-Dist: pydantic
Requires-Dist: PyYAML==6.0.2
Requires-Dist: python-dotenv==1.1.1
Requires-Dist: Jinja2==3.1.6
Requires-Dist: shellingham==1.5.4
Requires-Dist: tabulate>=0.9.0
Requires-Dist: colorama>=0.4.6
Requires-Dist: typer>=0.15.0
Requires-Dist: rich>=13.0.0
Requires-Dist: click>=8.0.0
Requires-Dist: pydantic>=2.0.0
Requires-Dist: PyYAML>=6.0
Requires-Dist: shellingham>=1.5.0
Requires-Dist: questionary>=1.10.0
Requires-Dist: prompt_toolkit>=3.0.50
Provides-Extra: enhanced
Requires-Dist: ipython>=8.0.0; extra == "enhanced"
Requires-Dist: colorama>=0.4.6; extra == "enhanced"
Requires-Dist: pygments>=2.15.0; extra == "enhanced"
Provides-Extra: dev
Requires-Dist: pytest>=7.0.0; extra == "dev"
Requires-Dist: pytest-cov>=4.0.0; extra == "dev"
Requires-Dist: pytest-asyncio>=0.21.0; extra == "dev"
Requires-Dist: pytest-benchmark>=4.0.0; extra == "dev"
Requires-Dist: pytest-mock>=3.10.0; extra == "dev"
Requires-Dist: black>=23.0.0; extra == "dev"
Requires-Dist: mypy>=1.0.0; extra == "dev"
Requires-Dist: ruff>=0.1.0; extra == "dev"
Provides-Extra: web
Requires-Dist: fastapi>=0.100.0; extra == "web"
Requires-Dist: uvicorn>=0.23.0; extra == "web"
Requires-Dist: websockets>=11.0; extra == "web"
Provides-Extra: docs
Requires-Dist: sphinx>=7.0.0; extra == "docs"
Requires-Dist: sphinx-rtd-theme>=1.3.0; extra == "docs"
Requires-Dist: myst-parser>=2.0.0; extra == "docs"
